vedro_dev/__init__.py
vedro_dev/__main__.py
vedro_dev/_dev_runner.py
vedro_dev/_module_reloader.py
vedro_dev/_protocol.py
vedro_dev/_step_scheduler.py
vedro_dev/_vedro_dev.py
vedro_dev/_web_socket_server.py
vedro_dev/py.typed
vedro_dev-0.2.2.dist-info/licenses/LICENSE
vedro_dev-0.2.2.dist-info/METADATA
vedro_dev-0.2.2.dist-info/WHEEL
vedro_dev-0.2.2.dist-info/top_level.txt
vedro_dev-0.2.2.dist-info/RECORD
